nrp_k8s_utils/__init__.py
nrp_k8s_utils/controller_manager.py
nrp_k8s_utils/ddl_controller.py
nrp_k8s_utils/kubectl_core.py
nrp_k8s_utils/pod_manager.py
nrp_k8s_utils/rsync_transfer_pod.py
nrp_k8s_utils/utils/__init__.py
nrp_k8s_utils/utils/key_generator.py
nrp_k8s_utils/utils/port_forwarding.py
nrp_k8s_utils-1.0.0.dist-info/METADATA
nrp_k8s_utils-1.0.0.dist-info/WHEEL
nrp_k8s_utils-1.0.0.dist-info/top_level.txt
nrp_k8s_utils-1.0.0.dist-info/RECORD
